pyisyox/__init__.py
pyisyox/__main__.py
pyisyox/clock.py
pyisyox/configuration.py
pyisyox/connection.py
pyisyox/constants.py
pyisyox/exceptions.py
pyisyox/isy.py
pyisyox/logging.py
pyisyox/networking.py
pyisyox/node_servers.py
pyisyox/py.typed
pyisyox/events/__init__.py
pyisyox/events/eventreader.py
pyisyox/events/router.py
pyisyox/events/strings.py
pyisyox/events/tcpsocket.py
pyisyox/events/websocket.py
pyisyox/helpers/__init__.py
pyisyox/helpers/entity.py
pyisyox/helpers/entity_platform.py
pyisyox/helpers/events.py
pyisyox/helpers/models.py
pyisyox/helpers/session.py
pyisyox/helpers/timeit.py
pyisyox/helpers/xml.py
pyisyox/nodes/__init__.py
pyisyox/nodes/folder.py
pyisyox/nodes/group.py
pyisyox/nodes/node.py
pyisyox/nodes/node_events.py
pyisyox/nodes/nodebase.py
pyisyox/programs/__init__.py
pyisyox/programs/folder.py
pyisyox/programs/program.py
pyisyox/util/__init__.py
pyisyox/util/backports.py
pyisyox/util/output.py
pyisyox/variables/__init__.py
pyisyox/variables/variable.py
pyisyox-1.0.0a10.dist-info/LICENSE.txt
pyisyox-1.0.0a10.dist-info/METADATA
pyisyox-1.0.0a10.dist-info/WHEEL
pyisyox-1.0.0a10.dist-info/top_level.txt
pyisyox-1.0.0a10.dist-info/RECORD
