Metadata-Version: 2.1
Name: pyisyox
Version: 1.0.0a10
Summary: Python module for asynchronous communication with Universal Devices, Inc.'s ISY & IoX controllers.
Home-page: https://github.com/shbatm/pyisyox
Author-email: Ryan Kraus <automicus@gmail.com>, shbatm <support@shbatm.com>
License: Apache-2.0
Project-URL: Source Code, https://github.com/shbatm/pyisyox
Project-URL: Homepage, https://github.com/shbatm/pyisyox
Keywords: home,automation,isy,isy994,isy-994,UDI,polisy,eisy,home-assistant
Classifier: Development Status :: 5 - Production/Stable
Classifier: Intended Audience :: End Users/Desktop
Classifier: Intended Audience :: Developers
Classifier: License :: OSI Approved :: Apache Software License
Classifier: Operating System :: OS Independent
Classifier: Programming Language :: Python
Classifier: Programming Language :: Python :: 3
Classifier: Topic :: Home Automation
Requires-Python: >=3.10
License-File: LICENSE.txt
Requires-Dist: aiohttp (>=3.8.1)
Requires-Dist: python-dateutil (>=2.8.1)
Requires-Dist: requests (>=2.28.1)
Requires-Dist: colorlog (>=6.6.0)
Requires-Dist: xmltodict (>=0.12.0)
